MANIFEST.in
board_sale_view.xml
res_config_view.xml
res_partner_view.xml
sale_data.xml
sale_demo.xml
sale_report.xml
sale_sequence.xml
sale_unit_test.xml
sale_view.xml
sale_workflow.xml
setup.py
./__init__.py
./__openerp__.py
./res_config.py
./res_partner.py
./sale.py
./edi/__init__.py
./edi/sale_order.py
./report/__init__.py
./report/sale_order.py
./report/sale_report.py
./wizard/__init__.py
./wizard/sale_line_invoice.py
./wizard/sale_make_invoice.py
./wizard/sale_make_invoice_advance.py
edi/sale_order_action_data.xml
i18n/ar.po
i18n/bg.po
i18n/bs.po
i18n/ca.po
i18n/cs.po
i18n/da.po
i18n/de.po
i18n/el.po
i18n/es.po
i18n/es_AR.po
i18n/es_BO.po
i18n/es_CL.po
i18n/es_CR.po
i18n/es_EC.po
i18n/es_MX.po
i18n/es_PE.po
i18n/es_VE.po
i18n/et.po
i18n/eu.po
i18n/fi.po
i18n/fr.po
i18n/gl.po
i18n/he.po
i18n/hi.po
i18n/hr.po
i18n/hu.po
i18n/id.po
i18n/is.po
i18n/it.po
i18n/ja.po
i18n/ko.po
i18n/lo.po
i18n/lt.po
i18n/lv.po
i18n/mk.po
i18n/mn.po
i18n/nb.po
i18n/nl.po
i18n/nl_BE.po
i18n/oc.po
i18n/pl.po
i18n/pt.po
i18n/pt_BR.po
i18n/ro.po
i18n/ru.po
i18n/sale.pot
i18n/sk.po
i18n/sl.po
i18n/sq.po
i18n/sr.po
i18n/sr@latin.po
i18n/sv.po
i18n/th.po
i18n/tlh.po
i18n/tr.po
i18n/uk.po
i18n/vi.po
i18n/zh_CN.po
i18n/zh_TW.po
images/Sale_order_line_to_invoice.jpeg
images/sale_dashboard.jpeg
images/sale_order.jpeg
images/sales_analysis.jpeg
openerp_sale.egg-info/PKG-INFO
openerp_sale.egg-info/SOURCES.txt
openerp_sale.egg-info/dependency_links.txt
openerp_sale.egg-info/requires.txt
openerp_sale.egg-info/top_level.txt
process/sale_process.xml
report/sale_order.rml
report/sale_order.sxw
report/sale_report_view.xml
security/ir.model.access.csv
security/sale_security.xml
static/src/img/icon.png
test/cancel_order.yml
test/delete_order.yml
test/edi_sale_order.yml
test/manual_order_policy.yml
test/sale_order_demo.yml
wizard/sale_line_invoice.xml
wizard/sale_make_invoice.xml
wizard/sale_make_invoice_advance.xml